slack_block_builder/__init__.py
slack_block_builder/action_block.py
slack_block_builder/body_parser.py
slack_block_builder/context_block.py
slack_block_builder/divider_block.py
slack_block_builder/exception.py
slack_block_builder/header_block.py
slack_block_builder/image_block.py
slack_block_builder/input_block.py
slack_block_builder/section_block.py
slack_block_builder/utils.py
slack_block_builder/components/__init__.py
slack_block_builder/components/block_element.py
slack_block_builder/components/composition_block.py
slack_block_builder/components/formatter.py
slack_block_builder/components/style.py
slack_block_builder/components/surface.py
tests/__init__.py
tests/integration_test/__init__.py
tests/integration_test/block_builder/__init__.py
tests/integration_test/block_builder/conftest.py
tests/integration_test/block_builder/test_apphome_builder.py
tests/integration_test/block_builder/test_block_builder.py
tests/integration_test/block_builder/test_modal_builder.py
tests/unittests/__init__.py
tests/unittests/conftest.py
tests/unittests/block_builder/__init__.py
tests/unittests/block_builder/conftest.py
tests/unittests/block_builder/test_action_block.py
tests/unittests/block_builder/test_body_parser.py
tests/unittests/block_builder/test_components__block_elements.py
tests/unittests/block_builder/test_components__composition_block.py
tests/unittests/block_builder/test_components__format.py
tests/unittests/block_builder/test_components__layout_attrs.py
tests/unittests/block_builder/test_components__style.py
tests/unittests/block_builder/test_components__surfaces.py
tests/unittests/block_builder/test_content_block.py
tests/unittests/block_builder/test_divider_block.py
tests/unittests/block_builder/test_header_block.py
tests/unittests/block_builder/test_image_block.py
tests/unittests/block_builder/test_input_block.py
tests/unittests/block_builder/test_section_block.py
slack_blocker_builder_SDK-0.1.0.dist-info/LICENSE
slack_blocker_builder_SDK-0.1.0.dist-info/METADATA
slack_blocker_builder_SDK-0.1.0.dist-info/WHEEL
slack_blocker_builder_SDK-0.1.0.dist-info/top_level.txt
slack_blocker_builder_SDK-0.1.0.dist-info/RECORD
